green_ysr/__init__.py
green_ysr/green_ysr.py
green_ysr-0.0.8.dist-info/METADATA
green_ysr-0.0.8.dist-info/WHEEL
green_ysr-0.0.8.dist-info/RECORD
