Metadata-Version: 2.1
Name: green-ysr
Version: 0.0.8
Summary: Green function model to calculate LDOS of multiple YSR impurites
Home-page: https://github.com/nanogunecic09/green-ysr
License: MIT
Author: stefanotriv
Author-email: s.trivini@nanogune.eu
Requires-Python: >=3.9,<4.0
Classifier: License :: OSI Approved :: MIT License
Classifier: Programming Language :: Python :: 3
Classifier: Programming Language :: Python :: 3.9
Classifier: Programming Language :: Python :: 3.10
Classifier: Programming Language :: Python :: 3.11
Classifier: Programming Language :: Python :: 3.12
